aiotgsdk/__init__.py
aiotgsdk/__version__.py
aiotgsdk-0.0.1.dist-info/LICENSE
aiotgsdk-0.0.1.dist-info/METADATA
aiotgsdk-0.0.1.dist-info/WHEEL
aiotgsdk-0.0.1.dist-info/top_level.txt
aiotgsdk-0.0.1.dist-info/RECORD
